argvsucks/__init__.py
argvsucks-0.230725.7.dist-info/LICENSE
argvsucks-0.230725.7.dist-info/METADATA
argvsucks-0.230725.7.dist-info/WHEEL
argvsucks-0.230725.7.dist-info/RECORD
